pq_spki/__init__.py
pq_spki-0.0.1.dist-info/METADATA
pq_spki-0.0.1.dist-info/WHEEL
pq_spki-0.0.1.dist-info/RECORD
